LICENSE
README.md
setup.py
fancify_text/__init__.py
fancify_text/cli.py
fancify_text/fontData.py
fancify_text/functions.py
fancify_text.egg-info/PKG-INFO
fancify_text.egg-info/SOURCES.txt
fancify_text.egg-info/dependency_links.txt
fancify_text.egg-info/entry_points.txt
fancify_text.egg-info/top_level.txt