Metadata-Version: 2.1
Name: fancify-text
Version: 1.0.0
Summary: Convert text to one of 27 fancy unicode representations
Home-page: https://github.com/Secret-chest/fancify-text
Author: Secret-chest
License: UNKNOWN
Platform: UNKNOWN
License-File: LICENSE
